[{"message":["Initialize new browser instance"],"level":"debug"},{"message":["Opening URL: https://auto1-training-1.auto1-test.com/en/merchant/signin"],"level":"info"},{"message":["Running single test case"],"level":"debug"},{"message":["Waiting for selector","form[name=user_signin]"],"level":"debug"},{"message":["Filling the from with selector #login-email"],"level":"debug"},{"message":["Filling the from with selector #login-password"],"level":"debug"},{"message":["Submiting a from using the selector button[type=submit].btn-primary"],"level":"debug"}]